{
	"data": {
		"relation": {
			"group": 0,
			"task": {
				"priority": 1
			}
		},
		"category": {
			"hosts": [
				".edu",
				".idv"
			],
			"schemes": [
				"ftps",
				"magnet"
			],
			"file-exts": [
				"torrent",
				"metalink"
			],
			"active-limit": 4,
			"finished-limit": 300,
			"recycled-limit": 300
		},
		"http": {
			"redirection-limit": 30
		},
		"proxy": {
			"port": 80,
			"type": 0
		},
		"common": {
			"name": "Downloads",
			"folder": "\/home\/blue\/Downloads",
			"connect-timeout": 15,
			"transmit-timeout": 30,
			"retry-delay": 4,
			"retry-limit": 4,
			"retry-count": 0,
			"max-connections": 1,
			"max-upload-speed": 0,
			"max-download-speed": 0,
			"timestamp": 1
		}
	},
	"children": [
	]
}

